CHANGES.txt
CREDITS.txt
LICENSE.txt
MANIFEST.in
README.rst
develop_requirements.txt
setup.cfg
setup.py
tox.ini
more/__init__.py
more.pathtool.egg-info/PKG-INFO
more.pathtool.egg-info/SOURCES.txt
more.pathtool.egg-info/dependency_links.txt
more.pathtool.egg-info/namespace_packages.txt
more.pathtool.egg-info/not-zip-safe
more.pathtool.egg-info/requires.txt
more.pathtool.egg-info/top_level.txt
more/pathtool/__init__.py
more/pathtool/main.py
more/pathtool/tests/test_path_tool.py