Metadata-Version: 1.1
Name: more.pathtool
Version: 0.6.1
Summary: Information about path configuration in Morepath
Home-page: https://github.com/morepath/more.pathtool
Author: Martijn Faassen
Author-email: faassen@startifact.com
License: BSD
Keywords: morepath
Platform: UNKNOWN
Classifier: Intended Audience :: Developers
Classifier: License :: OSI Approved :: BSD License
Classifier: Programming Language :: Python :: 2.7
Classifier: Programming Language :: Python :: 3.5
